rasqc/__init__.py
rasqc/base_checker.py
rasqc/check.py
rasqc/checksuite.py
rasqc/cli.py
rasqc/constants.py
rasqc/rasmodel.py
rasqc/registry.py
rasqc/result.py
rasqc/utils.py
rasqc/checkers/__init__.py
rasqc/checkers/hdfsync.py
rasqc/checkers/naming.py
rasqc/checkers/plan_settings.py
rasqc/checkers/projection.py
rasqc/checkers/stability.py
rasqc/checkers/stac_naming.py
rasqc/data/hms-naming-schema.json
rasqc/data/naming-schema.json
rasqc-0.0.4.dist-info/licenses/LICENSE
rasqc-0.0.4.dist-info/METADATA
rasqc-0.0.4.dist-info/WHEEL
rasqc-0.0.4.dist-info/entry_points.txt
rasqc-0.0.4.dist-info/top_level.txt
rasqc-0.0.4.dist-info/RECORD
