Metadata-Version: 2.4
Name: rasqc
Version: 0.0.4
Summary: Automated QA/QC for HEC-RAS Models.
Project-URL: repository, https://github.com/fema-ffrd/rasqc
Classifier: Development Status :: 4 - Beta
Classifier: Intended Audience :: Developers
Classifier: License :: OSI Approved :: MIT License
Classifier: Programming Language :: Python :: 3
Classifier: Programming Language :: Python :: 3.10
Classifier: Programming Language :: Python :: 3.11
Classifier: Programming Language :: Python :: 3.12
Classifier: Programming Language :: Python :: 3.13
License-File: LICENSE
Requires-Dist: rashdf
Requires-Dist: hydrostab
Requires-Dist: fsspec
Requires-Dist: rich
Requires-Dist: networkx
Requires-Dist: jsonschema
Requires-Dist: openpyxl
Requires-Dist: pystac
Requires-Dist: obstore==0.6.0
Provides-Extra: dev
Requires-Dist: pre-commit; extra == "dev"
Requires-Dist: ruff; extra == "dev"
Requires-Dist: pytest; extra == "dev"
Requires-Dist: pytest-cov; extra == "dev"
Dynamic: license-file
